blenderless/BUILD.bazel
blenderless/__init__.py
blenderless/blender_object.py
blenderless/camera.py
blenderless/cli.py
blenderless/geometry.py
blenderless/io.py
blenderless/main.py
blenderless/material.py
blenderless/scene.py
blenderless/utils.py
blenderless-0.1.8.dist-info/entry_points.txt
blenderless-0.1.8.dist-info/LICENSE
blenderless-0.1.8.dist-info/WHEEL
blenderless-0.1.8.dist-info/METADATA
blenderless-0.1.8.dist-info/RECORD
